twrpdtgen_v2/__init__.py
twrpdtgen_v2/__init__.py.replacebackup
twrpdtgen_v2/__main__.py
twrpdtgen_v2/__main__.py.replacebackup
twrpdtgen_v2/device_tree.py
twrpdtgen_v2/device_tree.py.replacebackup
twrpdtgen_v2/main.py
twrpdtgen_v2/main.py.replacebackup
twrpdtgen_v2/proprietary_files/elf.py
twrpdtgen_v2/proprietary_files/elf.py.replacebackup
twrpdtgen_v2/proprietary_files/get_vndk_libs.py
twrpdtgen_v2/proprietary_files/get_vndk_libs.py.replacebackup
twrpdtgen_v2/proprietary_files/ignore.py
twrpdtgen_v2/proprietary_files/ignore.py.replacebackup
twrpdtgen_v2/proprietary_files/proprietary_files_list.py
twrpdtgen_v2/proprietary_files/proprietary_files_list.py.replacebackup
twrpdtgen_v2/proprietary_files/section.py
twrpdtgen_v2/proprietary_files/section.py.replacebackup
twrpdtgen_v2/proprietary_files/sections/acdb.py
twrpdtgen_v2/proprietary_files/sections/acdb.py.replacebackup
twrpdtgen_v2/proprietary_files/sections/adsp.py
twrpdtgen_v2/proprietary_files/sections/adsp.py.replacebackup
twrpdtgen_v2/proprietary_files/sections/alarm.py
twrpdtgen_v2/proprietary_files/sections/alarm.py.replacebackup
twrpdtgen_v2/proprietary_files/sections/ant.py
twrpdtgen_v2/proprietary_files/sections/ant.py.replacebackup
twrpdtgen_v2/proprietary_files/sections/atrace.py
twrpdtgen_v2/proprietary_files/sections/atrace.py.replacebackup
twrpdtgen_v2/proprietary_files/sections/audio.py
twrpdtgen_v2/proprietary_files/sections/audio.py.replacebackup
twrpdtgen_v2/proprietary_files/sections/authsecret.py
twrpdtgen_v2/proprietary_files/sections/authsecret.py.replacebackup
twrpdtgen_v2/proprietary_files/sections/automotive.py
twrpdtgen_v2/proprietary_files/sections/automotive.py.replacebackup
twrpdtgen_v2/proprietary_files/sections/bluetooth.py
twrpdtgen_v2/proprietary_files/sections/bluetooth.py.replacebackup
twrpdtgen_v2/proprietary_files/sections/boot.py
twrpdtgen_v2/proprietary_files/sections/boot.py.replacebackup
twrpdtgen_v2/proprietary_files/sections/broadcastradio.py
twrpdtgen_v2-2.0.5.dist-info/METADATA
twrpdtgen_v2-2.0.5.dist-info/WHEEL
twrpdtgen_v2-2.0.5.dist-info/entry_points.txt
twrpdtgen_v2-2.0.5.dist-info/RECORD
