Metadata-Version: 2.1
Name: twrpdtgen_v2
Version: 2.0.5
Summary: Create an Android device tree from a device dump
Home-page: https://github.com/BiraruX/twrpdtgen_v2
License: Apache-2.0
Author: Biraru
Author-email: biraruyt@gmail.com
Requires-Python: >=3.8,<4.0
Classifier: License :: OSI Approved :: Apache Software License
Classifier: Programming Language :: Python :: 3
Classifier: Programming Language :: Python :: 3.8
Classifier: Programming Language :: Python :: 3.9
Classifier: Programming Language :: Python :: 3.10
Classifier: Programming Language :: Python :: 3.11
Classifier: Programming Language :: Python :: 3.12
Classifier: Programming Language :: Python :: 3.13
Requires-Dist: GitPython (>=3.1.31,<4.0.0)
Requires-Dist: Jinja2 (>=3.1.2,<4.0.0)
Requires-Dist: sebaubuntu-libs (>=1.4.4,<2.0.0)
Project-URL: Repository, https://github.com/BiraruX/twrpdtgen_v2
